clicr/__init__.py
clicr/clicr/build.py
clicr/clicr/command.py
clicr/clicr/config.py
clicr/clicr/init.py
clicr/clicr/init_template/README.md
clicr/clicr/init_template/__init__.py
clicr/clicr/init_template/config
clicr/clicr/init_template/main.py
clicr/clicr/init_template/pyproject.toml
clicr/clicr/install.py
clicr/clicr/main.py
clicr/clicr/package.py
clicr/clicr/repo.py
clicr/clicr/template.py
clicr/clicr/version.py
clicr/utils.py
clicr-0.0.2.dist-info/LICENSE
clicr-0.0.2.dist-info/METADATA
clicr-0.0.2.dist-info/WHEEL
clicr-0.0.2.dist-info/entry_points.txt
clicr-0.0.2.dist-info/RECORD
