Metadata-Version: 2.1
Name: clicr
Version: 0.0.2
Summary: Make effective CLI apps using Python
Home-page: https://syakyr.gitlab.io/clicr
License: Apache-2.0
Author: Syakyr Surani
Author-email: gitlab@amadeus-algo.com
Requires-Python: >=3.8,<4.0
Classifier: Development Status :: 1 - Planning
Classifier: License :: OSI Approved :: Apache Software License
Classifier: Programming Language :: Python :: 3
Classifier: Programming Language :: Python :: 3.8
Classifier: Programming Language :: Python :: 3.9
Classifier: Programming Language :: Python :: 3.10
Classifier: Programming Language :: Python :: 3.11
Classifier: Topic :: Software Development :: Build Tools
Classifier: Topic :: Software Development :: Libraries :: Python Modules
Requires-Dist: typer[all] (>=0.6.1,<0.7.0)
Project-URL: Documentation, https://syakyr.gitlab.io/clicr
Project-URL: Repository, https://gitlab.com/syakyr/clicr
